clode/__init__.py
clode/clode.py
clode/command_line.py
clode/errors.py
clode/search.py
git_clode-0.2.2.dist-info/licenses/LICENSE
git_clode-0.2.2.dist-info/METADATA
git_clode-0.2.2.dist-info/WHEEL
git_clode-0.2.2.dist-info/entry_points.txt
git_clode-0.2.2.dist-info/top_level.txt
git_clode-0.2.2.dist-info/RECORD
