Metadata-Version: 2.4
Name: git-clode
Version: 0.2.2
Summary: CLI tool to open git repositories quickly
Author: Oli
Author-email: Oli <oli@olillin.com>
Maintainer-email: Oli <oli@olillin.com>
License: MIT License
Project-URL: Bug Reports, https://github.com/olillin/clode/issues
Project-URL: Source, https://github.com/olillin/clode
Classifier: Development Status :: 7 - Inactive
Classifier: License :: OSI Approved :: MIT License
Classifier: Programming Language :: Python :: 3
License-File: LICENSE
Requires-Dist: colorama
Requires-Dist: inquirer
Dynamic: author
Dynamic: license-file
